{
  "type": "Feature",
  "properties": {
    "gn:admin1_code":"0.0",
    "gn:asciiname":"Katimahar",
    "gn:country_code":"BN",
    "gn:dem":1,
    "gn:feature_class":"P",
    "gn:feature_code":"PPL",
    "gn:name":"Katimahar",
    "gn:population":0,
    "gn:timezone":"Asia/Brunei",
    "iso:country":"BN",
    "name:msa_x_preferred":[
        "Kampung Katimahar"
    ],
    "name:msa_x_variant":[
        "Kampong Ketimahar"
    ],
    "wof:name":"Katimahar",
    "wof:placetype":"locality"
},
  "geometry": {"coordinates":[114.81453999999999,4.86807],"type":"Point"}
}