{
  "type": "Feature",
  "properties": {
    "gn:admin1_code":"0.0",
    "gn:asciiname":"Kampong Limpas",
    "gn:country_code":"BN",
    "gn:dem":13,
    "gn:feature_class":"P",
    "gn:feature_code":"PPL",
    "gn:name":"Kampong Limpas",
    "gn:population":0,
    "gn:timezone":"Asia/Brunei",
    "iso:country":"BN",
    "wof:name":"Kampong Limpas",
    "wof:placetype":"locality"
},
  "geometry": {"coordinates":[114.91667,4.83333],"type":"Point"}
}