{
  "type": "Feature",
  "properties": {
    "iso:country":"BN",
    "name:msa_x_preferred":[
        "Kampung Kilanas"
    ],
    "qs:gn_pop":0,
    "qs:name":"Kilanas",
    "qs:name_adm0":"Brunei",
    "qs:name_adm1":"Brunei-Muara",
    "qs:photos":231,
    "qs:photos_1k":47,
    "qs:photos_9k":1,
    "qs:photos_9r":4,
    "qs:photos_all":231,
    "qs:photos_sr":4,
    "qs:placetype":"Town",
    "qs:pop_sr":"0",
    "qs:woe_adm0":23424773,
    "wof:name":"Kilanas",
    "wof:placetype":"locality"
},
  "geometry": {"coordinates":[114.88950199999999,4.860833],"type":"Point"}
}