{
  "type": "Feature",
  "properties": {
    "gn:admin1_code":"0.0",
    "gn:asciiname":"Kampong Pangkalan Mau",
    "gn:cc2":"BN",
    "gn:country_code":"BN",
    "gn:dem":15,
    "gn:feature_class":"P",
    "gn:feature_code":"PPL",
    "gn:name":"Kampong Pangkalan Mau",
    "gn:population":0,
    "gn:timezone":"Asia/Brunei",
    "iso:country":"BN",
    "name:und_x_variant":[
        "Pengkalan Maut",
        "Kampong Pengkalan Maut",
        "Kampong Pangkalan Mau"
    ],
    "wof:name":"Kampong Pangkalan Mau",
    "wof:placetype":"locality"
},
  "geometry": {"coordinates":[114.73333,4.75],"type":"Point"}
}