{
  "type": "Feature",
  "properties": {
    "gn:admin1_code":"0.0",
    "gn:asciiname":"Kampong Sumbiling",
    "gn:country_code":"BN",
    "gn:dem":32,
    "gn:feature_class":"P",
    "gn:feature_code":"PPL",
    "gn:name":"Kampong Sumbiling",
    "gn:population":0,
    "gn:timezone":"Asia/Brunei",
    "iso:country":"BN",
    "wof:name":"Kampong Sumbiling",
    "wof:placetype":"locality"
},
  "geometry": {"coordinates":[115.11667,4.58333],"type":"Point"}
}