{
  "type": "Feature",
  "properties": {
    "gn:admin1_code":"0.0",
    "gn:asciiname":"Katok",
    "gn:country_code":"BN",
    "gn:dem":1,
    "gn:feature_class":"P",
    "gn:feature_code":"PPL",
    "gn:name":"Katok",
    "gn:population":0,
    "gn:timezone":"Asia/Brunei",
    "iso:country":"BN",
    "name:deu_x_preferred":[
        "Katok"
    ],
    "wof:name":"Katok",
    "wof:placetype":"locality"
},
  "geometry": {"coordinates":[114.89353,4.91619],"type":"Point"}
}