{
  "type": "Feature",
  "properties": {
    "iso:country":"BN",
    "label:eng_x_preferred_longname":[
        "Sengkurong Mukim"
    ],
    "label:eng_x_preferred_placetype":[
        "mukim"
    ],
    "name:deu_x_preferred":[
        "Sengkurong"
    ],
    "name:eng_x_preferred":[
        "Sengkurong"
    ],
    "name:eus_x_preferred":[
        "Sengkurong"
    ],
    "name:msa_x_preferred":[
        "Mukim Sengkurong"
    ],
    "name:nld_x_preferred":[
        "Sengkurong"
    ],
    "name:por_x_preferred":[
        "Sengkurong"
    ],
    "name:rus_x_preferred":[
        "\u0421\u0435\u043d\u0433\u043a\u0443\u0440\u043e\u043d\u0433"
    ],
    "name:ukr_x_preferred":[
        "\u0421\u0435\u043d\u0433\u043a\u0443\u0440\u043e\u043d\u0433"
    ],
    "qs:gn_pop":0,
    "qs:name":"Sengkurong",
    "qs:name_adm0":"Brunei",
    "qs:name_adm1":"Brunei-Muara",
    "qs:photos":2,
    "qs:photos_1k":1,
    "qs:photos_9k":7,
    "qs:photos_9r":8,
    "qs:photos_all":1636,
    "qs:photos_sr":1,
    "qs:placetype":"County",
    "qs:pop_sr":"0",
    "qs:woe_adm0":23424773,
    "statoids:country":"BN",
    "statoids:hasc":"BN.BM",
    "statoids:name":"Sengkurong",
    "statoids:timezone":"8",
    "statoids:type":"mukim",
    "wd:wordcount":224,
    "wof:name":"Sengkurong",
    "wof:placetype":"county",
    "wof:placetype_local":"mukim",
    "wof:shortcode":"SN"
},
  "geometry": {"coordinates":[114.864807,4.950037],"type":"Point"}
}