{
  "type": "Feature",
  "properties": {
    "gn:admin1_code":"0.0",
    "gn:asciiname":"Rumah Samawa",
    "gn:country_code":"BN",
    "gn:dem":56,
    "gn:feature_class":"P",
    "gn:feature_code":"PPL",
    "gn:name":"Rumah Samawa",
    "gn:population":0,
    "gn:timezone":"Asia/Brunei",
    "iso:country":"BN",
    "wof:name":"Rumah Samawa",
    "wof:placetype":"locality"
},
  "geometry": {"coordinates":[114.66667,4.23333],"type":"Point"}
}