{
  "type": "Feature",
  "properties": {
    "gn:admin1_code":"4.0",
    "gn:asciiname":"Kampong Kiudang",
    "gn:cc2":"BN",
    "gn:country_code":"BN",
    "gn:dem":15,
    "gn:feature_class":"P",
    "gn:feature_code":"PPL",
    "gn:name":"Kampong Kiudang",
    "gn:population":0,
    "gn:timezone":"Asia/Brunei",
    "iso:country":"BN",
    "name:und_x_variant":[
        "Kampong Kwidong",
        "Kampong Kuidang",
        "Kampong Kiudang"
    ],
    "wof:name":"Kampong Kiudang",
    "wof:placetype":"locality"
},
  "geometry": {"coordinates":[114.73333,4.75],"type":"Point"}
}