{
  "type": "Feature",
  "properties": {
    "gn:admin1_code":"0.0",
    "gn:asciiname":"Kampong Salapit",
    "gn:country_code":"BN",
    "gn:dem":10,
    "gn:feature_class":"P",
    "gn:feature_code":"PPL",
    "gn:name":"Kampong Salapit",
    "gn:population":0,
    "gn:timezone":"Asia/Brunei",
    "iso:country":"BN",
    "wof:name":"Kampong Salapit",
    "wof:placetype":"locality"
},
  "geometry": {"coordinates":[114.81667,4.86667],"type":"Point"}
}