{
  "type": "Feature",
  "properties": {
    "gn:admin1_code":"0.0",
    "gn:asciiname":"Tangki Ayer",
    "gn:country_code":"BN",
    "gn:dem":21,
    "gn:feature_class":"P",
    "gn:feature_code":"PPL",
    "gn:name":"Tangki Ayer",
    "gn:population":0,
    "gn:timezone":"Asia/Brunei",
    "iso:country":"BN",
    "wof:name":"Tangki Ayer",
    "wof:placetype":"locality"
},
  "geometry": {"coordinates":[114.93333,4.91667],"type":"Point"}
}