{
  "type": "Feature",
  "properties": {
    "gn:admin1_code":"0.0",
    "gn:asciiname":"Kampong Burong Pingai",
    "gn:cc2":"BN",
    "gn:country_code":"BN",
    "gn:dem":10,
    "gn:feature_class":"P",
    "gn:feature_code":"PPL",
    "gn:name":"Kampong Burong Pingai",
    "gn:population":0,
    "gn:timezone":"Asia/Brunei",
    "iso:country":"BN",
    "name:und_x_variant":[
        "Bang Pangan",
        "Kampong Bang Pangan",
        "Kampong Bupungan",
        "Kampong Bupangang",
        "Kampong Burong Pingai"
    ],
    "wof:name":"Kampong Burong Pingai",
    "wof:placetype":"locality"
},
  "geometry": {"coordinates":[114.63333,4.65],"type":"Point"}
}