{
  "type": "Feature",
  "properties": {
    "gn:admin1_code":"0.0",
    "gn:asciiname":"Kampong Kenua",
    "gn:cc2":"BN",
    "gn:country_code":"BN",
    "gn:dem":26,
    "gn:feature_class":"P",
    "gn:feature_code":"PPL",
    "gn:name":"Kampong Kenua",
    "gn:population":0,
    "gn:timezone":"Asia/Brunei",
    "iso:country":"BN",
    "name:und_x_variant":[
        "Kampong Menua",
        "Kampong Kenua"
    ],
    "wof:name":"Kampong Kenua",
    "wof:placetype":"locality"
},
  "geometry": {"coordinates":[115.05,4.61667],"type":"Point"}
}