{
  "type": "Feature",
  "properties": {
    "gn:admin1_code":"0.0",
    "gn:asciiname":"Kampong Perumpong",
    "gn:cc2":"BN",
    "gn:country_code":"BN",
    "gn:dem":13,
    "gn:feature_class":"P",
    "gn:feature_code":"PPL",
    "gn:name":"Kampong Perumpong",
    "gn:population":0,
    "gn:timezone":"Asia/Brunei",
    "iso:country":"BN",
    "name:und_x_variant":[
        "Perumpong",
        "Kampong Perumpang",
        "Kampong Perumpong"
    ],
    "wof:name":"Kampong Perumpong",
    "wof:placetype":"locality"
},
  "geometry": {"coordinates":[114.48333,4.68333],"type":"Point"}
}