{
  "type": "Feature",
  "properties": {
    "gn:admin1_code":"3.0",
    "gn:asciiname":"Kampong Batang Duri",
    "gn:country_code":"BN",
    "gn:dem":114,
    "gn:feature_class":"P",
    "gn:feature_code":"PPL",
    "gn:name":"Kampong Batang Duri",
    "gn:population":0,
    "gn:timezone":"Asia/Brunei",
    "iso:country":"BN",
    "wof:name":"Kampong Batang Duri",
    "wof:placetype":"locality"
},
  "geometry": {"coordinates":[115.13333,4.56667],"type":"Point"}
}