{
  "type": "Feature",
  "properties": {
    "gn:admin1_code":"2.0",
    "gn:admin2_code":"11821306.0",
    "gn:asciiname":"Subok",
    "gn:country_code":"BN",
    "gn:dem":1,
    "gn:feature_class":"P",
    "gn:feature_code":"PPL",
    "gn:name":"Subok",
    "gn:population":0,
    "gn:timezone":"Asia/Brunei",
    "iso:country":"BN",
    "name:msa_x_preferred":[
        "Kampung Subok"
    ],
    "name:msa_x_variant":[
        "Kampong Subok"
    ],
    "wof:name":"Subok",
    "wof:placetype":"locality"
},
  "geometry": {"coordinates":[114.96588,4.89311],"type":"Point"}
}