{
  "type": "Feature",
  "properties": {
    "iso:country":"BN",
    "qs:gn_country":"BN",
    "qs:gn_fcode":"PPL",
    "qs:gn_pop":0,
    "qs:name":"Kampong Keriam",
    "qs:name_adm0":"Brunei",
    "qs:name_adm1":"Tutong",
    "qs:photos":22,
    "qs:photos_1k":4,
    "qs:photos_9k":1,
    "qs:photos_9r":1,
    "qs:photos_all":22,
    "qs:photos_sr":1,
    "qs:placetype":"Town",
    "qs:pop_sr":"0",
    "qs:woe_adm0":23424773,
    "wof:name":"Kampong Keriam",
    "wof:placetype":"locality"
},
  "geometry": {"coordinates":[114.68333,4.81667],"type":"Point"}
}