{
  "type": "Feature",
  "properties": {
    "gn:admin1_code":"1.0",
    "gn:asciiname":"Sukang",
    "gn:country_code":"BN",
    "gn:dem":27,
    "gn:feature_class":"P",
    "gn:feature_code":"PPL",
    "gn:name":"Sukang",
    "gn:population":0,
    "gn:timezone":"Asia/Brunei",
    "iso:country":"BN",
    "wof:name":"Sukang",
    "wof:placetype":"locality"
},
  "geometry": {"coordinates":[114.61667,4.31667],"type":"Point"}
}