{
  "type": "Feature",
  "properties": {
    "gn:admin1_code":"0.0",
    "gn:asciiname":"Kampong Birau",
    "gn:cc2":"BN",
    "gn:country_code":"BN",
    "gn:dem":13,
    "gn:feature_class":"P",
    "gn:feature_code":"PPL",
    "gn:name":"Kampong Birau",
    "gn:population":0,
    "gn:timezone":"Asia/Brunei",
    "iso:country":"BN",
    "name:und_x_variant":[
        "Kampong Sentul",
        "Kampong Birau"
    ],
    "wof:name":"Kampong Birau",
    "wof:placetype":"locality"
},
  "geometry": {"coordinates":[114.73333,4.78333],"type":"Point"}
}