{
  "type": "Feature",
  "properties": {
    "gn:admin1_code":"4.0",
    "gn:asciiname":"Lubok Pulau",
    "gn:country_code":"BN",
    "gn:dem":1,
    "gn:feature_class":"P",
    "gn:feature_code":"PPL",
    "gn:name":"Lubok Pulau",
    "gn:population":0,
    "gn:timezone":"Asia/Brunei",
    "iso:country":"BN",
    "name:msa_x_preferred":[
        "Kampung Lubok Pulau"
    ],
    "name:msa_x_variant":[
        "Kampong Lubok Pulau"
    ],
    "wof:name":"Lubok Pulau",
    "wof:placetype":"locality"
},
  "geometry": {"coordinates":[114.66356,4.76403],"type":"Point"}
}