{
  "type": "Feature",
  "properties": {
    "gn:admin1_code":"0.0",
    "gn:asciiname":"Kampong Selangan",
    "gn:country_code":"BN",
    "gn:dem":37,
    "gn:feature_class":"P",
    "gn:feature_code":"PPL",
    "gn:name":"Kampong Selangan",
    "gn:population":0,
    "gn:timezone":"Asia/Brunei",
    "iso:country":"BN",
    "wof:name":"Kampong Selangan",
    "wof:placetype":"locality"
},
  "geometry": {"coordinates":[114.83333,4.91667],"type":"Point"}
}