{
  "type": "Feature",
  "properties": {
    "iso:country":"BN",
    "qs:gn_country":"BN",
    "qs:gn_fcode":"PPL",
    "qs:gn_pop":0,
    "qs:name":"Kampong Gadong",
    "qs:name_adm0":"Brunei",
    "qs:name_adm1":"Brunei-Muara",
    "qs:photos":1631,
    "qs:photos_1k":330,
    "qs:photos_9k":7,
    "qs:photos_9r":8,
    "qs:photos_all":1631,
    "qs:photos_sr":13,
    "qs:placetype":"Town",
    "qs:pop_sr":"0",
    "qs:woe_adm0":23424773,
    "wof:name":"Kampong Gadong",
    "wof:placetype":"locality"
},
  "geometry": {"coordinates":[114.91667,4.91667],"type":"Point"}
}